helga_alias
